{
  "collectionName": "components_components_footers",
  "info": {
    "displayName": "footer",
    "description": ""
  },
  "options": {},
  "attributes": {
    "link1": {
      "type": "string"
    },
    "logo1": {
      "type": "media",
      "multiple": false,
      "required": false,
      "allowedTypes": [
        "images"
      ]
    },
    "link2": {
      "type": "string"
    },
    "logo2": {
      "type": "media",
      "multiple": false,
      "required": false,
      "allowedTypes": [
        "images"
      ]
    },
    "link3": {
      "type": "string"
    },
    "logo3": {
      "allowedTypes": [
        "images"
      ],
      "type": "media",
      "multiple": false
    }
  }
}
